xnat_browser/__init__.py
xnat_browser/app_base.py
xnat_browser/browse_app.py
xnat_browser/browser.tcss
xnat_browser/constants.py
xnat_browser/create_markdown.py
xnat_browser/dicom_highlighter.py
xnat_browser/image_viewer.py
xnat_browser/io.py
xnat_browser/log_handler.py
xnat_browser/main.py
xnat_browser/query.tcss
xnat_browser/query_app.py
xnat_browser/screen.tcss
xnat_browser/screens.py
xnat_browser/search_entry.py
xnat_browser/sortable_data_table.py
xnat_browser/xnat_archive_tree.py
xnat_browser/xnat_plot.py
xnat_browser/xnat_prearchive_tree.py
xnat_browser/xnat_tree.py
xnat_browser-0.0.8.dist-info/LICENSE
xnat_browser-0.0.8.dist-info/METADATA
xnat_browser-0.0.8.dist-info/WHEEL
xnat_browser-0.0.8.dist-info/entry_points.txt
xnat_browser-0.0.8.dist-info/top_level.txt
xnat_browser-0.0.8.dist-info/RECORD
