Metadata-Version: 2.1
Name: xnat-browser
Version: 0.0.8
Summary: Browse XNAT in the terminal
Author-email: Patrick de Koning <pjhdekoning@lumc.nl>
Project-URL: Homepage, https://gitlab.com/lkeb/xnat_browser
Keywords: XNAT,TUI
Classifier: Operating System :: OS Independent
Classifier: Development Status :: 4 - Beta
Classifier: Intended Audience :: Developers
Classifier: Intended Audience :: Healthcare Industry
Classifier: Intended Audience :: Science/Research
Classifier: License :: OSI Approved :: MIT License
Classifier: Natural Language :: English
Classifier: Programming Language :: Python :: 3.10
Classifier: Environment :: Console
Classifier: Topic :: Scientific/Engineering :: Bio-Informatics
Classifier: Topic :: Scientific/Engineering :: Medical Science Apps.
Requires-Python: >=3.10
License-File: LICENSE
Requires-Dist: pandas
Requires-Dist: openpyxl
Requires-Dist: xnat
Requires-Dist: typer
Requires-Dist: textual
Requires-Dist: humanize
Requires-Dist: textual-fspicker
Requires-Dist: textual-plotext
Requires-Dist: textual-imageview
Requires-Dist: pylibjpeg[all]
